{"artist": "Slawomir Maniak", "availability": ["arena", "mtgo", "paper"], "borderColor": "black", "colorIdentity": ["B", "G"], "colors": ["G"], "convertedManaCost": 1.0, "edhrecRank": 1943, "finishes": ["nonfoil", "foil"], "foreignData": [{"language": "German", "multiverseId": 544814, "name": "Ausgraben", "text": "Abspalten {1}{B}{B}{G}\nDurchsuche deine Bibliothek nach einer Standardland-Karte, zeige sie offen vor, nimm sie auf deine Hand und mische danach.", "type": "Hexerei"}, {"language": "French", "multiverseId": 544875, "name": "D\u00e9terrer", "text": "Tranchage {1}{B}{B}{G}\nCherchez dans votre biblioth\u00e8que une carte de terrain de base, r\u00e9v\u00e9lez-la, mettez-la dans votre main, puis m\u00e9langez.", "type": "Rituel"}, {"language": "Japanese", "multiverseId": 544936, "name": "\u6398\u308a\u8d77\u3053\u3057", "text": "\u5207\u9664{1}{B}{B}{G}\n\u3042\u306a\u305f\u306e\u30e9\u30a4\u30d6\u30e9\u30ea\u30fc\u304b\u3089\uff3b\u57fa\u672c\u571f\u5730\u30fb\uff3d\u30ab\u30fc\u30c9\uff11\u679a\u3092\u63a2\u3057\u3001\uff3b\u516c\u958b\u3057\u3001\uff3d\u3042\u306a\u305f\u306e\u624b\u672d\u306b\u52a0\u3048\u308b\u3002\u305d\u306e\u5f8c\u3001\u30e9\u30a4\u30d6\u30e9\u30ea\u30fc\u3092\u5207\u308a\u76f4\u3059\u3002", "type": "\u30bd\u30fc\u30b5\u30ea\u30fc"}], "frameEffects": ["extendedart"], "frameVersion": "2015", "hasFoil": true, "hasNonFoil": true, "identifiers": {"cardKingdomFoilId": "253173", "cardKingdomId": "252427", "cardsphereId": "82586", "mcmId": "581339", "mcmMetaId": "346589", "mtgjsonV4Id": "67dea2ed-afab-5a3a-afd6-9aed5046e3fb", "multiverseId": "544753", "scryfallId": "078d0194-0137-45cd-977a-eefae67f9bca", "scryfallIllustrationId": "0b54a0f0-9e0e-4c1f-882d-ba54205f7e6d", "scryfallOracleId": "ae96fe7e-8d89-4f44-9cc4-3c9b124fdc4b", "tcgplayerProductId": "252928"}, "isStarter": true, "keywords": ["Cleave"], "language": "English", "layout": "normal", "legalities": {"alchemy": "Legal", "brawl": "Legal", "commander": "Legal", "duel": "Legal", "explorer": "Legal", "future": "Legal", "gladiator": "Legal", "historic": "Legal", "historicbrawl": "Legal", "legacy": "Legal", "modern": "Legal", "penny": "Legal", "pioneer": "Legal", "standard": "Legal", "vintage": "Legal"}, "manaCost": "{G}", "manaValue": 1.0, "name": "Dig Up", "number": "387", "originalText": "Cleave {1}{B}{B}{G}\nSearch your library for a basic land card, [reveal it,] put it into your hand, then shuffle.", "originalType": "Sorcery", "printings": ["DBL", "PRM", "PVOW", "VOW"], "promoTypes": ["boosterfun"], "purchaseUrls": {"cardKingdom": "https://mtgjson.com/links/8513ede473976ce5", "cardKingdomFoil": "https://mtgjson.com/links/f9432c8839c9594d", "cardmarket": "https://mtgjson.com/links/76cd85c61bd1b7db", "tcgplayer": "https://mtgjson.com/links/1d38ab78cc6ba01b"}, "rarity": "rare", "rulings": [{"date": "2021-11-19", "text": "If you paid the cleave cost, you must put a card into your hand as Dig Up resolves (assuming there is at least one card in your library)."}, {"date": "2021-11-19", "text": "If you cast a spell for its cleave cost, that spell doesn't have any of the text in square brackets while it's on the stack."}, {"date": "2021-11-19", "text": "A cleave cost is an alternative cost that's paid instead of the spell's mana cost. Casting a spell for its cleave cost doesn't change the spell's mana value."}, {"date": "2021-11-19", "text": "You can't cast a spell for both its cleave cost and another alternative cost. For example, if an effect gives an Alchemist's Retrieval in your graveyard a flashback cost of {U}, you can't cast it from your graveyard for its cleave cost."}, {"date": "2021-11-19", "text": "If an effect allows you to \u201ccast a spell without paying its mana cost,\u201d you can't cast that spell for its cleave cost."}], "securityStamp": "oval", "setCode": "VOW", "subtypes": [], "supertypes": [], "text": "Cleave {1}{B}{B}{G} (You may cast this spell for its cleave cost. If you do, remove the words in square brackets.)\nSearch your library for a [basic land] card, [reveal it,] put it into your hand, then shuffle.", "type": "Sorcery", "types": ["Sorcery"], "uuid": "c3df45d8-8056-53c8-a21b-ee478e51613d", "variations": ["34a499a5-8f9b-51b7-9d32-d70b031e5141"]}