{"artist": "Tom W\u00e4nerstrand", "availability": ["mtgo"], "boosterTypes": ["draft"], "borderColor": "black", "colorIdentity": [], "colors": [], "convertedManaCost": 4.0, "edhrecRank": 17659, "finishes": ["nonfoil", "foil"], "flavorText": "It is like life and destiny: we think we know the story, but we have read only half the tale.", "foreignData": [], "frameVersion": "2015", "hasFoil": true, "hasNonFoil": true, "identifiers": {"mtgjsonV4Id": "0a5eec81-affc-5db2-9630-83fea8ad9b0b", "mtgoFoilId": "56597", "mtgoId": "56596", "multiverseId": "397542", "scryfallId": "89dbf782-3f94-4043-8852-0390ce2e4d87", "scryfallIllustrationId": "13a5f3c3-3665-4f60-babe-b291807bae67", "scryfallOracleId": "9b7634bf-067b-4b5c-be72-ff1b80247969"}, "isOnlineOnly": true, "isReprint": true, "language": "English", "layout": "normal", "legalities": {"commander": "Legal", "duel": "Legal", "legacy": "Legal", "penny": "Legal", "premodern": "Legal", "vintage": "Legal"}, "manaCost": "{4}", "manaValue": 4.0, "name": "Emmessi Tome", "number": "221", "originalText": "{5}, {T}: Draw two cards, then discard a card.", "originalType": "Artifact", "printings": ["EMA", "MB1", "TMP", "TPR"], "purchaseUrls": {}, "rarity": "uncommon", "rulings": [], "setCode": "TPR", "subtypes": [], "supertypes": [], "text": "{5}, {T}: Draw two cards, then discard a card.", "type": "Artifact", "types": ["Artifact"], "uuid": "442ff5f8-bf3f-53d6-a2c0-6ae1dc7f647d"}