{"artist": "Scott M. Fischer", "availability": ["mtgo", "paper"], "boosterTypes": ["draft"], "borderColor": "black", "colorIdentity": ["U"], "colors": ["U"], "convertedManaCost": 3.0, "edhrecRank": 1228, "finishes": ["nonfoil", "foil"], "flavorText": "When a strong mind moves, form and energy shift to heed it.", "foreignData": [{"flavorText": "Wenn sich ein starker Geist bewegt, passen sich Form und Energie achtsam daran an.", "language": "German", "multiverseId": 105255, "name": "Vom Reellen befreit", "text": "{U}: Tappe die verzauberte Kreatur.\n{U}: Enttappe die verzauberte Kreatur.", "type": "Kreaturenverzauberung"}, {"flavorText": "Cuando una mente fuerte se mueve, la forma y la energ\u00eda se alteran para obedecerle.", "language": "Spanish", "multiverseId": 105915, "name": "Liberado de lo real", "text": "{U}: Gira la criatura encantada.\n{U}: Endereza la criatura encantada.", "type": "Encantar criatura"}, {"flavorText": "Quand un esprit fort se d\u00e9place, la forme et l'\u00e9nergie se courbent pour l'\u00e9couter.", "language": "French", "multiverseId": 105090, "name": "Lib\u00e9r\u00e9 du r\u00e9el", "text": "{U} : Engagez la cr\u00e9ature enchant\u00e9e.\n{U} : D\u00e9gagez la cr\u00e9ature enchant\u00e9e.", "type": "Enchanter : cr\u00e9ature"}, {"flavorText": "Quando una mente potente si muove, la forma e l'energia si spostano per prestarle attenzione.", "language": "Italian", "multiverseId": 105420, "name": "Libero dalla Realt\u00e0", "text": "{U}: TAPpa la creatura incantata.\n{U}: STAPpa la creatura incantata.", "type": "Incanta Creatura"}, {"flavorText": "\u5f37\u3044\u610f\u5fd7\u304c\u52d5\u304d\u3092\u898b\u305b\u308b\u3068\u304d\u3001\u59ff\u3084\u529b\u306f\u305d\u308c\u306b\u5f93\u3046\u3002", "language": "Japanese", "multiverseId": 105585, "name": "\u73fe\u5b9f\u304b\u3089\u306e\u904a\u96e2", "text": "{U}\uff1a\u30a8\u30f3\u30c1\u30e3\u30f3\u30c8\u3055\u308c\u3066\u3044\u308b\u30af\u30ea\u30fc\u30c1\u30e3\u30fc\u3092\u30bf\u30c3\u30d7\u3059\u308b\u3002\n{U}\uff1a\u30a8\u30f3\u30c1\u30e3\u30f3\u30c8\u3055\u308c\u3066\u3044\u308b\u30af\u30ea\u30fc\u30c1\u30e3\u30fc\u3092\u30a2\u30f3\u30bf\u30c3\u30d7\u3059\u308b\u3002", "type": "\u30a8\u30f3\u30c1\u30e3\u30f3\u30c8\uff08\u30af\u30ea\u30fc\u30c1\u30e3\u30fc\uff09"}, {"flavorText": "Quando uma mente forte se move, a forma e a energia mudam para observ\u00e1-la.", "language": "Portuguese (Brazil)", "multiverseId": 105750, "name": "Libertos da Realidade", "text": "{U}: Vira a criatura encantada.\n{U}: Desvira a criatura encantada.", "type": "Encantar Criatura"}, {"flavorText": "\u5f62\u4f53\u4e0e\u80fd\u91cf\u5c06\u968f\u575a\u5f3a\u5fc3\u7075\u800c\u884c\u3002", "language": "Chinese Simplified", "multiverseId": 104925, "name": "\u9038\u8131\u5b9e\u754c", "text": "{U}\uff1a\u6a2a\u7f6e\u53d7\u6b64\u7ed3\u754c\u7684\u751f\u7269\u3002\n{U}\uff1a\u91cd\u7f6e\u53d7\u6b64\u7ed3\u754c\u7684\u751f\u7269\u3002", "type": "\u751f\u7269\u7ed3\u754c"}], "frameVersion": "2003", "hasFoil": true, "hasNonFoil": true, "identifiers": {"cardKingdomFoilId": "117375", "cardKingdomId": "117044", "cardsphereId": "39967", "mcmId": "12665", "mcmMetaId": "7256", "mtgjsonV4Id": "9f800c64-27ce-507e-96fb-7c0a3e2a8332", "mtgoFoilId": "22157", "mtgoId": "22156", "multiverseId": "87336", "scryfallId": "e9ecee02-12c0-4aed-a679-41bce95e0cda", "scryfallIllustrationId": "14d6bf38-ffd8-455d-80f5-feb060afe396", "scryfallOracleId": "03d32ace-dd99-48c6-bcae-9b915d041aef", "tcgplayerProductId": "12437"}, "keywords": ["Enchant"], "language": "English", "layout": "normal", "legalities": {"commander": "Legal", "duel": "Legal", "legacy": "Legal", "modern": "Legal", "pauper": "Legal", "paupercommander": "Legal", "vintage": "Legal"}, "manaCost": "{2}{U}", "manaValue": 3.0, "name": "Freed from the Real", "number": "38", "originalText": "{U}: Tap enchanted creature.\n{U}: Untap enchanted creature.", "originalType": "Enchant Creature", "printings": ["A25", "SLD", "SOK"], "purchaseUrls": {"cardKingdom": "https://mtgjson.com/links/6fab79a8b02da506", "cardKingdomFoil": "https://mtgjson.com/links/d299687da1c711c3", "cardmarket": "https://mtgjson.com/links/d7ed2dd75ade0f32", "tcgplayer": "https://mtgjson.com/links/36699bce5649ea43"}, "rarity": "common", "rulings": [{"date": "2018-03-16", "text": "Only the player who controls Freed from the Real can activate its abilities. This might not be the controller of the enchanted creature."}], "setCode": "SOK", "subtypes": ["Aura"], "supertypes": [], "text": "Enchant creature\n{U}: Tap enchanted creature.\n{U}: Untap enchanted creature.", "type": "Enchantment \u2014 Aura", "types": ["Enchantment"], "uuid": "f60214cf-c219-54da-9a49-3aa198aa26b9"}