{"artist": "Randy Vargas", "availability": ["arena", "mtgo", "paper"], "boosterTypes": ["draft"], "borderColor": "black", "colorIdentity": ["W"], "colors": ["W"], "convertedManaCost": 3.0, "edhrecRank": 23366, "finishes": ["nonfoil", "foil"], "flavorText": "A plus-one is simply not enough.", "foreignData": [{"flavorText": "Eine Begleitperson ist einfach nicht genug.", "language": "German", "multiverseId": 555475, "name": "Zunehmendes Gedr\u00e4nge", "text": "Wenn das Zunehmende Gedr\u00e4nge ins Spiel kommt, kannst du deine Bibliothek nach einer beliebigen Anzahl an Karten namens Zunehmendes Gedr\u00e4nge durchsuchen, sie offen vorzeigen, auf deine Hand nehmen und danach mischen.", "type": "Kreatur \u2014 Mensch, B\u00fcrger"}, {"flavorText": "Un solo acompa\u00f1ante no es suficiente.", "language": "Spanish", "multiverseId": 555736, "name": "Multitud reunida", "text": "Cuando la Multitud reunida entre al campo de batalla, puedes buscar en tu biblioteca cualquier cantidad de cartas llamadas Multitud reunida, mostrarlas, ponerlas en tu mano y luego barajar.", "type": "Criatura \u2014 Ciudadano humano"}, {"flavorText": "Venir accompagn\u00e9 d'une seule personne, c'est trop peu.", "language": "French", "multiverseId": 555997, "name": "Cohue mondaine", "text": "Quand la Cohue mondaine arrive sur le champ de bataille, vous pouvez chercher dans votre biblioth\u00e8que n'importe quel nombre de cartes appel\u00e9es Cohue mondaine, les r\u00e9v\u00e9ler, les mettre dans votre main, puis m\u00e9langer.", "type": "Cr\u00e9ature : humain et citoyen"}, {"flavorText": "A volte un solo accompagnatore non \u00e8 proprio sufficiente.", "language": "Italian", "multiverseId": 556258, "name": "Calca Crescente", "text": "Quando la Calca Crescente entra nel campo di battaglia, puoi passare in rassegna il tuo grimorio per un qualsiasi numero di carte chiamate Calca Crescente, rivelarle e aggiungerle alla tua mano, poi rimescolare.", "type": "Creatura \u2014 Cittadino Umano"}, {"flavorText": "\u4e00\u4eba\u540c\u4f34\u53ef\u3067\u306f\u3001\u5358\u7d14\u306b\u8db3\u308a\u306a\u3044\u3002", "language": "Japanese", "multiverseId": 556519, "name": "\u96c6\u307e\u308b\u7fa4\u8846", "text": "\u96c6\u307e\u308b\u7fa4\u8846\u304c\u6226\u5834\u306b\u51fa\u305f\u3068\u304d\u3001\u3042\u306a\u305f\u306f\u300c\u3042\u306a\u305f\u306e\u30e9\u30a4\u30d6\u30e9\u30ea\u30fc\u304b\u3089\u300e\u96c6\u307e\u308b\u7fa4\u8846\u300f\u3068\u3044\u3046\u540d\u524d\u3092\u6301\u3064\u671b\u3080\u679a\u6570\u306e\u30ab\u30fc\u30c9\u3092\u63a2\u3057\u3001\u516c\u958b\u3057\u3001\u3042\u306a\u305f\u306e\u624b\u672d\u306b\u52a0\u3048\u308b\u3002\u305d\u306e\u5f8c\u3001\u30e9\u30a4\u30d6\u30e9\u30ea\u30fc\u3092\u5207\u308a\u76f4\u3059\u3002\u300d\u3092\u9078\u3093\u3067\u3082\u3088\u3044\u3002", "type": "\u30af\u30ea\u30fc\u30c1\u30e3\u30fc \u2014 \u4eba\u9593\u30fb\u5e02\u6c11"}, {"flavorText": "\ub3d9\ubc18\uc778 \ud55c \uba85\uc73c\ub85c\ub294 \ucda9\ubd84\ud558\uc9c0 \uc54a\ub2e4.", "language": "Korean", "multiverseId": 556780, "name": "\ubaa8\uc5ec\ub4dc\ub294 \uc778\ud30c", "text": "\ubaa8\uc5ec\ub4dc\ub294 \uc778\ud30c\uac00 \uc804\uc7a5\uc5d0 \ub4e4\uc5b4\uc62c \ub54c, \ub2f9\uc2e0\uc740 \ub2f9\uc2e0\uc758 \uc11c\uace0\uc5d0\uc11c \uc774\ub984\uc774 \ubaa8\uc5ec\ub4dc\ub294 \uc778\ud30c\uc778 \uce74\ub4dc\ub97c \uc6d0\ud558\ub294 \uc218\ub9cc\ud07c \ucc3e\uc544 \uacf5\uac1c\ud55c \ud6c4, \ub2f9\uc2e0\uc758 \uc190\uc73c\ub85c \uac00\uc838\uac08 \uc218 \uc788\ub2e4. \uadf8\ub807\uac8c \ud55c\ub2e4\uba74, \uc11c\uace0\ub97c \uc11e\ub294\ub2e4.", "type": "\uc0dd\ubb3c \u2014 \uc778\uac04 \uc2dc\ubbfc"}, {"flavorText": "S\u00f3 mais um n\u00e3o basta.", "language": "Portuguese (Brazil)", "multiverseId": 557041, "name": "Turba em Forma\u00e7\u00e3o", "text": "Quando Turba em Forma\u00e7\u00e3o entra no campo de batalha, voc\u00ea pode procurar em seu grim\u00f3rio qualquer n\u00famero de cards com o nome Turba em Forma\u00e7\u00e3o, revel\u00e1-los, coloc\u00e1-los em sua m\u00e3o e depois embaralhar.", "type": "Criatura \u2014 Humano Cidad\u00e3o"}, {"flavorText": "\u00ab\u041f\u043b\u044e\u0441 \u043e\u0434\u0438\u043d\u00bb \u0431\u044b\u0432\u0430\u0435\u0442 \u043f\u0440\u043e\u0441\u0442\u043e \u043d\u0435\u0434\u043e\u0441\u0442\u0430\u0442\u043e\u0447\u043d\u043e.", "language": "Russian", "multiverseId": 557302, "name": "\u0421\u043e\u0431\u0438\u0440\u0430\u044e\u0449\u0430\u044f\u0441\u044f \u0422\u043e\u043b\u043f\u0430", "text": "\u041a\u043e\u0433\u0434\u0430 \u0421\u043e\u0431\u0438\u0440\u0430\u044e\u0449\u0430\u044f\u0441\u044f \u0422\u043e\u043b\u043f\u0430 \u0432\u044b\u0445\u043e\u0434\u0438\u0442 \u043d\u0430 \u043f\u043e\u043b\u0435 \u0431\u0438\u0442\u0432\u044b, \u0432\u044b \u043c\u043e\u0436\u0435\u0442\u0435 \u043d\u0430\u0439\u0442\u0438 \u0432 \u0432\u0430\u0448\u0435\u0439 \u0431\u0438\u0431\u043b\u0438\u043e\u0442\u0435\u043a\u0435 \u043b\u044e\u0431\u043e\u0435 \u043a\u043e\u043b\u0438\u0447\u0435\u0441\u0442\u0432\u043e \u043a\u0430\u0440\u0442 \u0441 \u0438\u043c\u0435\u043d\u0435\u043c \u0421\u043e\u0431\u0438\u0440\u0430\u044e\u0449\u0430\u044f\u0441\u044f \u0422\u043e\u043b\u043f\u0430, \u043f\u043e\u043a\u0430\u0437\u0430\u0442\u044c \u0438\u0445, \u043f\u043e\u043b\u043e\u0436\u0438\u0442\u044c \u0438\u0445 \u0432 \u0432\u0430\u0448\u0443 \u0440\u0443\u043a\u0443, \u0437\u0430\u0442\u0435\u043c \u043f\u0435\u0440\u0435\u0442\u0430\u0441\u043e\u0432\u0430\u0442\u044c \u0431\u0438\u0431\u043b\u0438\u043e\u0442\u0435\u043a\u0443.", "type": "\u0421\u0443\u0449\u0435\u0441\u0442\u0432\u043e \u2014 \u0427\u0435\u043b\u043e\u0432\u0435\u043a \u0413\u0440\u0430\u0436\u0434\u0430\u043d\u0438\u043d"}, {"flavorText": "\u53ea\u6709\u4e00\u4eba\u8bf4\u300c\u6211\u4e5f\u6765\u300d\u8fdc\u8fdc\u4e0d\u591f\u3002", "language": "Chinese Simplified", "multiverseId": 557563, "name": "\u96c6\u7fa4\u6c11\u4f17", "text": "\u5f53\u96c6\u7fa4\u6c11\u4f17\u8fdb\u6218\u573a\u65f6\uff0c\u4f60\u53ef\u4ee5\u4ece\u4f60\u724c\u5e93\u4e2d\u641c\u5bfb\u4efb\u610f\u6570\u91cf\u540d\u79f0\u4e3a\u96c6\u7fa4\u6c11\u4f17\u7684\u724c\uff0c\u5c55\u793a\u8fd9\u4e9b\u724c\uff0c\u5c06\u5b83\u4eec\u7f6e\u4e8e\u4f60\u624b\u4e0a\uff0c\u7136\u540e\u6d17\u724c\u3002", "type": "\u751f\u7269 \uff5e\u4eba\u7c7b\uff0f\u5e02\u6c11"}, {"flavorText": "\u53ea\u6709\u4e00\u4eba\u8aaa\u300c\u6211\u4e5f\u4f86\u300d\u9060\u9060\u4e0d\u5920\u3002", "language": "Chinese Traditional", "multiverseId": 557824, "name": "\u96c6\u7fa4\u6c11\u773e", "text": "\u7576\u96c6\u7fa4\u6c11\u773e\u9032\u6230\u5834\u6642\uff0c\u4f60\u53ef\u4ee5\u5f9e\u4f60\u724c\u5eab\u4e2d\u641c\u5c0b\u4efb\u610f\u6578\u91cf\u540d\u7a31\u70ba\u96c6\u7fa4\u6c11\u773e\u7684\u724c\uff0c\u5c55\u793a\u9019\u4e9b\u724c\uff0c\u5c07\u5b83\u5011\u7f6e\u65bc\u4f60\u624b\u4e0a\uff0c\u7136\u5f8c\u6d17\u724c\u3002", "type": "\u751f\u7269 \uff5e\u4eba\u985e\uff0f\u5e02\u6c11"}], "frameVersion": "2015", "hasFoil": true, "hasNonFoil": true, "identifiers": {"cardKingdomFoilId": "259083", "cardKingdomId": "258746", "cardsphereId": "86800", "mcmId": "652155", "mcmMetaId": "406769", "mtgArenaId": "80164", "mtgjsonV4Id": "89dc69c9-f3a1-5d77-bd3d-ebe081c2c388", "mtgoId": "98245", "multiverseId": "555214", "scryfallId": "290347b9-d3cc-4882-8da6-9d8b8677f276", "scryfallIllustrationId": "954af71e-8c69-48e8-8435-07c10680447e", "scryfallOracleId": "bbd340ce-cf06-43df-a060-be80bc46e985", "tcgplayerProductId": "269059"}, "language": "English", "layout": "normal", "legalities": {"alchemy": "Legal", "brawl": "Legal", "commander": "Legal", "duel": "Legal", "explorer": "Legal", "future": "Legal", "gladiator": "Legal", "historic": "Legal", "historicbrawl": "Legal", "legacy": "Legal", "modern": "Legal", "pauper": "Legal", "paupercommander": "Legal", "penny": "Legal", "pioneer": "Legal", "standard": "Legal", "vintage": "Legal"}, "manaCost": "{2}{W}", "manaValue": 3.0, "name": "Gathering Throng", "number": "13", "originalText": "When Gathering Throng enters the battlefield, you may search your library for any number of cards named Gathering Throng, reveal them, put them into your hand, then shuffle.", "originalType": "Creature \u2014 Human Citizen", "power": "3", "printings": ["SNC"], "purchaseUrls": {"cardKingdom": "https://mtgjson.com/links/e5c3f0a88b7e60f0", "cardKingdomFoil": "https://mtgjson.com/links/508c61ac209a9913", "cardmarket": "https://mtgjson.com/links/9c5a6282789649a3", "tcgplayer": "https://mtgjson.com/links/b4949524f179e9e7"}, "rarity": "common", "rulings": [], "setCode": "SNC", "subtypes": ["Human", "Citizen"], "supertypes": [], "text": "When Gathering Throng enters the battlefield, you may search your library for any number of cards named Gathering Throng, reveal them, put them into your hand, then shuffle.", "toughness": "1", "type": "Creature \u2014 Human Citizen", "types": ["Creature"], "uuid": "c6da916a-a190-5813-9eba-3d8729b6ddde"}