{"artist": "Eric Deschamps", "availability": ["mtgo", "paper"], "boosterTypes": ["draft"], "borderColor": "black", "colorIdentity": ["W"], "colors": ["W"], "convertedManaCost": 7.0, "edhrecRank": 11475, "finishes": ["nonfoil", "foil"], "flavorText": "\"You are unworthy of life, but take heart. You have earned a clean death.\"", "foreignData": [{"flavorText": "\u201eDu bist des Lebens unw\u00fcrdig, aber fasse Mut. Du hast einen schnellen Tod verdient.\"", "language": "German", "multiverseId": 522351, "name": "Glorreiche Vollstreckerin", "text": "Fliegend, Lebensverkn\u00fcpfung\nZu Beginn jedes Kampfes und falls du mehr Lebenspunkte als ein Gegner hast, erh\u00e4lt die Glorreiche Vollstreckerin Doppelschlag bis zum Ende des Zuges.", "type": "Kreatur \u2014 Engel"}, {"flavorText": "\"No te mereces vivir, pero an\u00edmate: te has ganado una muerte r\u00e1pida\".", "language": "Spanish", "multiverseId": 522612, "name": "Ejecutora gloriosa", "text": "Vuela, v\u00ednculo vital.\nAl comienzo de cada combate, si tienes m\u00e1s vidas que un oponente, la Ejecutora gloriosa gana la habilidad de da\u00f1ar dos veces hasta el final del turno.", "type": "Criatura \u2014 \u00c1ngel"}, {"flavorText": "\u00ab Tu ne m\u00e9rites pas de vivre, mais haut les c\u0153urs. Tu as m\u00e9rit\u00e9 une belle mort. \u00bb", "language": "French", "multiverseId": 522873, "name": "Argousine glorieuse", "text": "Vol, lien de vie\nAu d\u00e9but de chaque combat, si vous avez plus de points de vie qu'un adversaire, l'Argousine glorieuse acquiert la double initiative jusqu'\u00e0 la fin du tour.", "type": "Cr\u00e9ature : ange"}, {"flavorText": "\"Non meriti la vita, ma non temere. Ti sei meritato una morte rapida.\"", "language": "Italian", "multiverseId": 523134, "name": "Esecutrice Gloriosa", "text": "Volare, legame vitale\nAll'inizio di ogni combattimento, se hai pi\u00f9 punti vita di un avversario, l'Esecutrice Gloriosa ha doppio attacco fino alla fine del turno.", "type": "Creatura \u2014 Angelo"}, {"flavorText": "\u300c\u3042\u306a\u305f\u306f\u751f\u304d\u308b\u306b\u5024\u3057\u307e\u305b\u3093\u304c\u3001\u5b89\u5fc3\u306a\u3055\u3044\u3002\u7dba\u9e97\u306a\u6b7b\u3092\u52dd\u3061\u5f97\u307e\u3057\u305f\u3002\u300d", "language": "Japanese", "multiverseId": 523395, "name": "\u6804\u5149\u306e\u57f7\u884c\u5b98", "text": "\u98db\u884c\u3001\u7d46\u9b42\n\u5404\u6226\u95d8\u306e\u958b\u59cb\u6642\u306b\u3001\u3042\u306a\u305f\u306e\u30e9\u30a4\u30d5\u304c\u5bfe\u6226\u76f8\u624b\uff11\u4eba\u3088\u308a\u3082\u591a\u3044\u5834\u5408\u3001\u30bf\u30fc\u30f3\u7d42\u4e86\u6642\u307e\u3067\u3001\u6804\u5149\u306e\u57f7\u884c\u5b98\u306f\u4e8c\u6bb5\u653b\u6483\u3092\u5f97\u308b\u3002", "type": "\u30af\u30ea\u30fc\u30c1\u30e3\u30fc \u2014 \u5929\u4f7f"}, {"flavorText": "\"\ub108\ub294 \uc0b4 \uac00\uce58\uac00 \uc5c6\uc9c0\ub9cc, \uae30\uc6b4\uc744 \ub0b4\ub77c. \uae68\ub057\ud55c \uc8fd\uc74c\uc744 \uc5bb\uac8c \ub418\uc5c8\uc73c\ub2c8.\"", "language": "Korean", "multiverseId": 523656, "name": "\uc601\uad11\uc2a4\ub7ec\uc6b4 \uc9d1\ud589\uc790", "text": "\ube44\ud589, \uc0dd\uba85\uc5f0\uacb0\n\uac01 \uc804\ud22c \uc2dc\uc791\uc5d0, \ub2f9\uc2e0\uc774 \uc0c1\ub300\ubcf4\ub2e4 \ub9ce\uc740 \uc0dd\uba85\uc810\uc744 \uac00\uc9c0\uace0 \uc788\ub2e4\uba74, \uc601\uad11\uc2a4\ub7ec\uc6b4 \uc9d1\ud589\uc790\ub294 \ud134\uc885\ub8cc\uae4c\uc9c0 \uc774\ub2e8\uacf5\uaca9\uc744 \uc5bb\ub294\ub2e4.", "type": "\uc0dd\ubb3c \u2014 \ucc9c\uc0ac"}, {"flavorText": "\"Voc\u00ea n\u00e3o merece viver, mas console-se. Voc\u00ea fez por merecer uma morte limpa.\"", "language": "Portuguese (Brazil)", "multiverseId": 523917, "name": "Impositora Gloriosa", "text": "Voar, v\u00ednculo com a vida\nNo in\u00edcio de cada combate, se voc\u00ea tem mais pontos de vida que um oponente, Impositora Gloriosa ganha golpe duplo at\u00e9 o final do turno.", "type": "Criatura \u2014 Anjo"}, {"flavorText": "\u00ab\u0422\u044b \u043d\u0435\u0434\u043e\u0441\u0442\u043e\u0438\u043d \u0436\u0438\u0437\u043d\u0438, \u043d\u043e \u043d\u0435 \u0441\u0442\u043e\u0438\u0442 \u0433\u043e\u0440\u0435\u0432\u0430\u0442\u044c. \u0422\u044b \u0437\u0430\u0441\u043b\u0443\u0436\u0438\u043b \u0447\u0438\u0441\u0442\u0443\u044e \u0441\u043c\u0435\u0440\u0442\u044c\u00bb.", "language": "Russian", "multiverseId": 524178, "name": "\u0421\u043b\u0430\u0432\u043d\u0430\u044f \u0411\u043b\u044e\u0441\u0442\u0438\u0442\u0435\u043b\u044c\u043d\u0438\u0446\u0430", "text": "\u041f\u043e\u043b\u0435\u0442, \u0426\u0435\u043f\u044c \u0436\u0438\u0437\u043d\u0438\n\u0412 \u043d\u0430\u0447\u0430\u043b\u0435 \u043a\u0430\u0436\u0434\u043e\u0433\u043e \u0431\u043e\u044f, \u0435\u0441\u043b\u0438 \u0443 \u0432\u0430\u0441 \u0431\u043e\u043b\u044c\u0448\u0435 \u0436\u0438\u0437\u043d\u0435\u0439, \u0447\u0435\u043c \u0443 \u043e\u043f\u043f\u043e\u043d\u0435\u043d\u0442\u0430, \u0442\u043e \u0421\u043b\u0430\u0432\u043d\u0430\u044f \u0411\u043b\u044e\u0441\u0442\u0438\u0442\u0435\u043b\u044c\u043d\u0438\u0446\u0430 \u043f\u043e\u043b\u0443\u0447\u0430\u0435\u0442 \u0414\u0432\u043e\u0439\u043d\u043e\u0439 \u0443\u0434\u0430\u0440 \u0434\u043e \u043a\u043e\u043d\u0446\u0430 \u0445\u043e\u0434\u0430.", "type": "\u0421\u0443\u0449\u0435\u0441\u0442\u0432\u043e \u2014 \u0410\u043d\u0433\u0435\u043b"}, {"flavorText": "\u300c\u4f60\u4e0d\u914d\u6d3b\u7740\uff0c\u4f46\u522b\u6c14\u9981\u3002\u4f60\u80fd\u6b7b\u5f97\u5e72\u8106\u3002\u300d", "language": "Chinese Simplified", "multiverseId": 524439, "name": "\u8f89\u714c\u6267\u6cd5\u4f7f", "text": "\u98de\u884c\uff0c\u7cfb\u547d\n\u5728\u6bcf\u6b21\u6218\u6597\u5f00\u59cb\u65f6\uff0c\u82e5\u4f60\u7684\u751f\u547d\u6bd4\u67d0\u5bf9\u624b\u591a\uff0c\u5219\u8f89\u714c\u6267\u6cd5\u4f7f\u83b7\u5f97\u8fde\u51fb\u5f02\u80fd\u76f4\u5230\u56de\u5408\u7ed3\u675f\u3002", "type": "\u751f\u7269 \uff5e\u5929\u4f7f"}, {"flavorText": "\u300c\u4f60\u4e0d\u914d\u6d3b\u8457\uff0c\u4f46\u5225\u6c23\u9912\u3002\u4f60\u80fd\u6b7b\u5f97\u4e7e\u8106\u3002\u300d", "language": "Chinese Traditional", "multiverseId": 524700, "name": "\u8f1d\u714c\u57f7\u6cd5\u4f7f", "text": "\u98db\u884c\uff0c\u7e6b\u547d\n\u5728\u6bcf\u6b21\u6230\u9b25\u958b\u59cb\u6642\uff0c\u82e5\u4f60\u7684\u751f\u547d\u6bd4\u67d0\u5c0d\u624b\u591a\uff0c\u5247\u8f1d\u714c\u57f7\u6cd5\u4f7f\u7372\u5f97\u9023\u64ca\u7570\u80fd\u76f4\u5230\u56de\u5408\u7d50\u675f\u3002", "type": "\u751f\u7269 \uff5e\u5929\u4f7f"}], "frameVersion": "2015", "hasFoil": true, "hasNonFoil": true, "identifiers": {"cardKingdomFoilId": "246946", "cardKingdomId": "246341", "cardsphereId": "77716", "mcmId": "566473", "mcmMetaId": "341601", "mtgjsonV4Id": "60a72140-b54c-5d3b-8b15-f416eec5b203", "mtgoId": "90397", "multiverseId": "522090", "scryfallId": "de1365aa-e814-471b-8c9e-cf4c5011bcc3", "scryfallIllustrationId": "01a5976a-9d99-4d1a-8577-08224b2beb89", "scryfallOracleId": "3dcbbbeb-4efe-4363-bfb4-b7d7f803bafa", "tcgplayerProductId": "239960"}, "keywords": ["Flying", "Lifelink"], "language": "English", "layout": "normal", "legalities": {"commander": "Legal", "duel": "Legal", "gladiator": "Legal", "historic": "Legal", "historicbrawl": "Legal", "legacy": "Legal", "modern": "Legal", "paupercommander": "Restricted", "penny": "Legal", "vintage": "Legal"}, "manaCost": "{5}{W}{W}", "manaValue": 7.0, "name": "Glorious Enforcer", "number": "14", "originalText": "Flying, lifelink\nAt the beginning of each combat, if you have more life than an opponent, Glorious Enforcer gains double strike until end of turn.", "originalType": "Creature \u2014 Angel", "power": "5", "printings": ["J21", "MH2"], "purchaseUrls": {"cardKingdom": "https://mtgjson.com/links/806c00fe2d5b6ec5", "cardKingdomFoil": "https://mtgjson.com/links/ad0bd74893179b17", "cardmarket": "https://mtgjson.com/links/67c983b93d3db6e0", "tcgplayer": "https://mtgjson.com/links/86fb523604713b7f"}, "rarity": "uncommon", "rulings": [{"date": "2021-06-18", "text": "Glorious Enforcer's triggered ability checks whether you have more life than an opponent at the beginning of each combat to see if it triggers. If you don't, the ability won't trigger at all. The ability will check again as it tries to resolve. If you don't at that time, the ability won't do anything. You must have more life than an opponent at both times for Glorious Enforcer to get double strike. It does not, however, need to be the same opponent both times."}, {"date": "2021-06-18", "text": "After the triggered ability resolves, Glorious Enforcer will continue to have double strike until the end of the turn no matter what players' life totals are."}], "setCode": "MH2", "subtypes": ["Angel"], "supertypes": [], "text": "Flying, lifelink\nAt the beginning of each combat, if you have more life than an opponent, Glorious Enforcer gains double strike until end of turn.", "toughness": "5", "type": "Creature \u2014 Angel", "types": ["Creature"], "uuid": "77c306d7-9b1c-5a29-a62b-70dc0bc2bd9f"}