{"artist": "Greg Staples", "availability": ["mtgo"], "boosterTypes": ["draft"], "borderColor": "black", "colorIdentity": ["R"], "colors": ["R"], "convertedManaCost": 4.0, "edhrecRank": 13644, "finishes": ["nonfoil", "foil"], "flavorText": "Giant-sized body. Goblin-sized brain.", "foreignData": [], "frameVersion": "2015", "hasFoil": true, "hasNonFoil": true, "identifiers": {"mtgjsonV4Id": "1668bf62-ac91-5821-bfd5-552f335f400f", "mtgoFoilId": "53128", "mtgoId": "53127", "multiverseId": "382958", "scryfallId": "3159acb5-7ab6-4998-834a-2e46f35502c7", "scryfallIllustrationId": "02d872b5-bdd8-42b1-a091-1ad85c39ac08", "scryfallOracleId": "e91bcf01-113b-4532-9f78-2a155b17be4f"}, "isOnlineOnly": true, "isReprint": true, "language": "English", "layout": "normal", "legalities": {"commander": "Legal", "duel": "Legal", "gladiator": "Legal", "historic": "Legal", "historicbrawl": "Legal", "legacy": "Legal", "paupercommander": "Restricted", "penny": "Legal", "premodern": "Legal", "vintage": "Legal"}, "manaCost": "{3}{R}", "manaValue": 4.0, "name": "Goblin Goon", "number": "166", "originalText": "Goblin Goon can't attack unless you control more creatures than defending player.\nGoblin Goon can't block unless you control more creatures than attacking player.", "originalType": "Creature \u2014 Goblin Mutant", "power": "6", "printings": ["DDT", "JMP", "LGN", "PZ2", "VMA"], "purchaseUrls": {}, "rarity": "uncommon", "rulings": [], "setCode": "VMA", "subtypes": ["Goblin", "Mutant"], "supertypes": [], "text": "Goblin Goon can't attack unless you control more creatures than defending player.\nGoblin Goon can't block unless you control more creatures than attacking player.", "toughness": "6", "type": "Creature \u2014 Goblin Mutant", "types": ["Creature"], "uuid": "276c9671-ac07-573a-8042-2cbec01a45af"}