{"artist": "Adam Rex", "availability": ["mtgo", "paper"], "borderColor": "black", "colorIdentity": ["B"], "colors": ["B"], "convertedManaCost": 6.0, "edhrecRank": 4059, "finishes": ["nonfoil"], "flavorText": "The warlocks never expected their creations to create servants of their own.", "foreignData": [], "frameVersion": "2015", "hasFoil": false, "hasNonFoil": true, "identifiers": {"cardKingdomId": "271809", "mcmId": "688974", "mcmMetaId": "2508", "mtgjsonV4Id": "d37ce3b4-a05a-5e22-97b1-5667f9651389", "mtgoFoilId": "103737", "mtgoId": "103736", "scryfallId": "e1241a23-f2da-4920-9383-b5994d7160af", "scryfallIllustrationId": "be903b4a-8b12-446b-a426-59aadf871804", "scryfallOracleId": "4235c99b-50de-4190-8938-3ce5ec5c5248", "tcgplayerProductId": "456824"}, "isReprint": true, "isStarter": true, "language": "English", "layout": "normal", "legalities": {"commander": "Legal", "duel": "Legal", "legacy": "Legal", "premodern": "Legal", "vintage": "Legal"}, "manaCost": "{4}{B}{B}", "manaValue": 6.0, "name": "Gravespawn Sovereign", "number": "79", "power": "3", "printings": ["MIC", "ONS", "PLIST", "SCD"], "purchaseUrls": {"cardKingdom": "https://mtgjson.com/links/3d95f5a14474e75a", "cardmarket": "https://mtgjson.com/links/0546407dab177f34", "tcgplayer": "https://mtgjson.com/links/2b32c6963d4f9673"}, "rarity": "rare", "rulings": [{"date": "2004-10-04", "text": "Since the ability does not have the {T} symbol, you can use the ability before this creature begins a turn under your control."}, {"date": "2004-10-04", "text": "It can tap itself but is not required to do so."}], "securityStamp": "oval", "setCode": "SCD", "subtypes": ["Zombie"], "supertypes": [], "text": "Tap five untapped Zombies you control: Put target creature card from a graveyard onto the battlefield under your control.", "toughness": "3", "type": "Creature \u2014 Zombie", "types": ["Creature"], "uuid": "ff9e0407-d196-5a93-8eec-bb9cba061df5"}