{"artist": "Ryan Barger", "availability": ["mtgo", "paper"], "boosterTypes": ["draft"], "borderColor": "black", "colorIdentity": [], "colors": [], "convertedManaCost": 1.0, "edhrecRank": 15336, "finishes": ["nonfoil", "foil"], "flavorText": "\"It sees all, but it reveals what it sees only to a chosen few.\"\n\u2014Taigam, Ojutai master", "foreignData": [{"flavorText": "\u201eEr sieht alles, doch offenbart es nur wenigen Auserw\u00e4hlten.\" \u2014Taigam, Ojutai-Meister", "language": "German", "multiverseId": 395398, "name": "H\u00fcter der Linse", "text": "Du kannst dir verdeckte Kreaturen, die du nicht kontrollierst, anschauen. (Du kannst dies jederzeit tun.)", "type": "Artefaktkreatur \u2014 Golem"}, {"flavorText": "\"Lo ve todo, pero solo revela sus descubrimientos a unos pocos\". \u2014Taigam, maestro de \u00d3jutai", "language": "Spanish", "multiverseId": 397246, "name": "Guardi\u00e1n de la lente", "text": "Puedes mirar las criaturas boca abajo que no controlas. (Puedes hacer esto en cualquier momento.)", "type": "Criatura artefacto \u2014 G\u00f3lem"}, {"flavorText": "\u00ab Elle voit tout, mais ne r\u00e9v\u00e8le ce qu'elle voit qu'\u00e0 quelques \u00e9lus. \u00bb \u2014Taigam, ma\u00eetre d'Ojuta\u00ef", "language": "French", "multiverseId": 395662, "name": "Gardien de la Lentille", "text": "Vous pouvez regarder les cr\u00e9atures face cach\u00e9e que vous ne contr\u00f4lez pas. (Vous pouvez faire ceci \u00e0 tout moment.)", "type": "Cr\u00e9ature-artefact : golem"}, {"flavorText": "\"Vede tutto, ma rivela ci\u00f2 che scorge solo a pochi eletti.\" \u2014Taigam, maestro Ojutai", "language": "Italian", "multiverseId": 395926, "name": "Custode della Lente", "text": "Puoi guardare le creature a faccia in gi\u00f9 che non controlli. (Puoi farlo in qualsiasi momento.)", "type": "Creatura Artefatto \u2014 Golem"}, {"flavorText": "\u300c\u305d\u308c\u306f\u3059\u3079\u3066\u3092\u898b\u901a\u3059\u304c\u3001\u9650\u3089\u308c\u305f\u5c11\u6570\u306e\u8005\u305f\u3061\u306b\u306e\u307f\u898b\u305f\u3082\u306e\u3092\u958b\u793a\u3059\u308b\u3002\u300d \u2015\u2015\u30aa\u30b8\u30e5\u30bf\u30a4\u306e\u9054\u4eba\u3001\u30c6\u30a4\u30ac\u30e0", "language": "Japanese", "multiverseId": 396190, "name": "\u6c34\u6676\u306e\u756a\u4eba", "text": "\u3042\u306a\u305f\u306f\u3042\u306a\u305f\u304c\u30b3\u30f3\u30c8\u30ed\u30fc\u30eb\u3057\u3066\u3044\u306a\u3044\u88cf\u5411\u304d\u306e\u30af\u30ea\u30fc\u30c1\u30e3\u30fc\u306e\u8868\u5074\u3092\u898b\u3066\u3082\u3088\u3044\u3002\uff08\u3053\u308c\u306f\u3044\u3064\u3067\u3082\u884c\u3063\u3066\u3088\u3044\u3002\uff09", "type": "\u30a2\u30fc\u30c6\u30a3\u30d5\u30a1\u30af\u30c8\u30fb\u30af\u30ea\u30fc\u30c1\u30e3\u30fc \u2014 \u30b4\u30fc\u30ec\u30e0"}, {"flavorText": "\"\ub80c\uc988\ub294 \ubaa8\ub4e0 \uac83\uc744 \ubcf4\uc9c0\ub9cc \uc120\ud0dd\ub41c \uc18c\uc218\ub9cc\uc774 \ub80c\uc988\ub97c \ud1b5\ud574 \ubcfc \uc218 \uc788\ub2e4.\" \u2014\uc624\uc8fc\ud0c0\uc774 \uc2a4\uc2b9 \ud0c0\uc774\uac10", "language": "Korean", "multiverseId": 396454, "name": "\ub80c\uc988 \uc9c0\ud0b4\uc774", "text": "\ub2f9\uc2e0\uc740 \ub2f9\uc2e0\uc774 \uc870\uc885\ud558\uc9c0 \uc54a\ub294 \ub4b7\uba74 \uc0c1\ud0dc\uc778 \uc0dd\ubb3c\ub4e4\uc758 \uc55e\uba74\uc744 \ubcfc \uc218 \uc788\ub2e4. (\ub2f9\uc2e0\uc740 \uc5b8\uc81c\ub4e0\uc9c0 \uc774\ub807\uac8c \ud560 \uc218 \uc788\ub2e4.)", "type": "\ub9c8\ubc95\ubb3c\uccb4 \uc0dd\ubb3c \u2014 \uace8\ub818"}, {"flavorText": "\"Ele v\u00ea tudo, mas s\u00f3 revela o que v\u00ea a alguns poucos privilegiados.\" \u2014 Taigam, mestre de Ojutai", "language": "Portuguese (Brazil)", "multiverseId": 396718, "name": "Guardi\u00e3o da Lente", "text": "Voc\u00ea pode olhar as criaturas voltadas para baixo que voc\u00ea n\u00e3o controla. (Voc\u00ea pode fazer isso a qualquer momento.)", "type": "Criatura Artefato \u2014 Golem"}, {"flavorText": "\u00ab\u041e\u043d \u0432\u0438\u0434\u0438\u0442 \u0432\u0441\u0435, \u043d\u043e \u0434\u0435\u043b\u0438\u0442\u0441\u044f \u0442\u0435\u043c, \u0447\u0442\u043e \u0432\u0438\u0434\u0438\u0442, \u043b\u0438\u0448\u044c \u0441 \u043d\u0435\u043c\u043d\u043e\u0433\u0438\u043c\u0438 \u0438\u0437\u0431\u0440\u0430\u043d\u043d\u044b\u043c\u0438\u00bb. \u2014 \u0422\u0430\u0439\u0433\u0430\u043c, \u043e\u0434\u0436\u0443\u0442\u0430\u0439\u0441\u043a\u0438\u0439 \u043c\u0430\u0441\u0442\u0435\u0440", "language": "Russian", "multiverseId": 396982, "name": "\u0425\u0440\u0430\u043d\u0438\u0442\u0435\u043b\u044c \u041b\u0438\u043d\u0437\u044b", "text": "\u0412\u044b \u043c\u043e\u0436\u0435\u0442\u0435 \u0441\u043c\u043e\u0442\u0440\u0435\u0442\u044c \u043d\u0430\u0445\u043e\u0434\u044f\u0449\u0438\u0435\u0441\u044f \u0440\u0443\u0431\u0430\u0448\u043a\u043e\u0439 \u0432\u0432\u0435\u0440\u0445 \u0441\u0443\u0449\u0435\u0441\u0442\u0432\u0430 \u043d\u0435 \u043f\u043e\u0434 \u0432\u0430\u0448\u0438\u043c \u043a\u043e\u043d\u0442\u0440\u043e\u043b\u0435\u043c. (\u0412\u044b \u043c\u043e\u0436\u0435\u0442\u0435 \u0434\u0435\u043b\u0430\u0442\u044c \u044d\u0442\u043e \u0432 \u043b\u044e\u0431\u043e\u0435 \u0432\u0440\u0435\u043c\u044f.)", "type": "\u0410\u0440\u0442\u0435\u0444\u0430\u043a\u0442 \u0421\u0443\u0449\u0435\u0441\u0442\u0432\u043e \u2014 \u0413\u043e\u043b\u0435\u043c"}, {"flavorText": "\u300c\u5b83\u89c1\u5f97\u4e07\u7269\uff0c\u4f46\u53ea\u6709\u5c11\u6570\u4eba\u9009\u624d\u80fd\u900f\u8fc7\u5b83\u5f97\u89c1\u4e00\u5207\u3002\u300d \uff5e\u6b27\u795d\u6cf0\u65cf\u5b97\u5e08\u6cf0\u4f3d\u59c6", "language": "Chinese Simplified", "multiverseId": 394870, "name": "\u900f\u955c\u5b88\u536b", "text": "\u4f60\u53ef\u4ee5\u68c0\u89c6\u4e0d\u7531\u4f60\u64cd\u63a7\u4e14\u724c\u9762\u671d\u4e0b\u7684\u751f\u7269\u3002\uff08\u4f60\u53ef\u4ee5\u968f\u65f6\u5982\u6b64\u4f5c\u3002\uff09", "type": "\u795e\u5668\u751f\u7269\uff5e\u9b54\u50cf"}, {"flavorText": "\u300c\u5b83\u898b\u5f97\u842c\u7269\uff0c\u4f46\u53ea\u6709\u5c11\u6578\u4eba\u9078\u624d\u80fd\u900f\u904e\u5b83\u5f97\u898b\u4e00\u5207\u3002\u300d \uff5e\u6b50\u795d\u6cf0\u65cf\u5b97\u5e2b\u6cf0\u4f3d\u59c6", "language": "Chinese Traditional", "multiverseId": 395134, "name": "\u900f\u93e1\u5b88\u885b", "text": "\u4f60\u53ef\u4ee5\u6aa2\u8996\u4e0d\u7531\u4f60\u64cd\u63a7\u4e14\u724c\u9762\u671d\u4e0b\u7684\u751f\u7269\u3002\uff08\u4f60\u53ef\u4ee5\u96a8\u6642\u5982\u6b64\u4f5c\u3002\uff09", "type": "\u795e\u5668\u751f\u7269\uff5e\u9b54\u50cf"}], "frameVersion": "2015", "hasFoil": true, "hasNonFoil": true, "identifiers": {"cardKingdomFoilId": "199847", "cardKingdomId": "199474", "cardsphereId": "13799", "mcmId": "273410", "mcmMetaId": "211370", "mtgjsonV4Id": "4839c984-5107-5328-87d4-2a6315dcbd93", "mtgoFoilId": "55963", "mtgoId": "55962", "multiverseId": "394606", "scryfallId": "86d6c502-ae3e-4e67-8f1d-3323b4468f72", "scryfallIllustrationId": "5e5e15b2-0c41-449c-b310-6ccb37f635b0", "scryfallOracleId": "84b28100-ad70-4a78-b557-99f5ef6126a3", "tcgplayerProductId": "96691"}, "language": "English", "layout": "normal", "legalities": {"commander": "Legal", "duel": "Legal", "legacy": "Legal", "modern": "Legal", "pauper": "Legal", "paupercommander": "Legal", "penny": "Legal", "pioneer": "Legal", "vintage": "Legal"}, "manaCost": "{1}", "manaValue": 1.0, "name": "Keeper of the Lens", "number": "240", "originalText": "You may look at face-down creatures you don't control. (You may do this at any time.)", "originalType": "Artifact Creature \u2014 Golem", "power": "1", "printings": ["DTK"], "purchaseUrls": {"cardKingdom": "https://mtgjson.com/links/095d3d0396f28b56", "cardKingdomFoil": "https://mtgjson.com/links/c1158544442bfad1", "cardmarket": "https://mtgjson.com/links/f9e7867db83c213c", "tcgplayer": "https://mtgjson.com/links/8031eb17102d8194"}, "rarity": "common", "rulings": [{"date": "2015-02-25", "text": "Keeper of the Lens allows you to look at face-down creatures you don\u2019t control whenever you want to, even if you don\u2019t have priority. This action doesn\u2019t use the stack."}, {"date": "2015-02-25", "text": "Keeper of the Lens doesn\u2019t stop your opponents from looking at face-down creatures they control."}, {"date": "2015-02-25", "text": "Keeper of the Lens doesn\u2019t let you look at other players\u2019 face-down spells while they\u2019re on the stack."}], "setCode": "DTK", "subtypes": ["Golem"], "supertypes": [], "text": "You may look at face-down creatures you don't control any time.", "toughness": "2", "type": "Artifact Creature \u2014 Golem", "types": ["Artifact", "Creature"], "uuid": "1d377c83-74b6-58d0-8abd-a13f38adc9d3"}