{"artist": "Cosmin Podar", "availability": ["paper"], "borderColor": "borderless", "colorIdentity": [], "colors": [], "convertedManaCost": 0.0, "edhrecRank": 10, "finishes": ["foil"], "foreignData": [], "frameVersion": "2015", "hasFoil": true, "hasNonFoil": false, "identifiers": {"cardKingdomFoilId": "264717", "cardsphereId": "92704", "mcmId": "678253", "mtgjsonV4Id": "b232be17-8e54-5af6-a806-6a5bd5b05d63", "scryfallId": "ffb1ddf8-7a58-4440-9b60-ba77e12e7a0e", "scryfallIllustrationId": "78052b39-2767-40a5-bdef-3a5e63745ec3", "scryfallOracleId": "c23e5b80-08d2-4e24-9908-fe2aa4f30f6f", "tcgplayerProductId": "282746"}, "isReprint": true, "language": "English", "layout": "normal", "legalities": {"commander": "Legal", "duel": "Legal", "explorer": "Legal", "gladiator": "Legal", "historic": "Legal", "historicbrawl": "Legal", "legacy": "Legal", "modern": "Legal", "penny": "Legal", "pioneer": "Legal", "vintage": "Legal"}, "manaValue": 0.0, "name": "Reliquary Tower", "number": "695", "originalReleaseDate": "2021-06-21", "printings": ["40K", "BRC", "C14", "C15", "C16", "C19", "C20", "C21", "CLB", "CM2", "CMR", "CON", "DMC", "F13", "M13", "M19", "MB1", "PHED", "PLG20", "PM19", "PRM", "SLD"], "purchaseUrls": {"cardKingdomFoil": "https://mtgjson.com/links/510f9be3c21e0dba", "tcgplayer": "https://mtgjson.com/links/2d1741ed507e7ffa"}, "rarity": "rare", "rulings": [{"date": "2009-02-01", "text": "If multiple effects modify your hand size, apply them in timestamp order. For example, if you put Null Profusion (an enchantment that says your maximum hand size is two) onto the battlefield and then put Reliquary Tower onto the battlefield, you'll have no maximum hand size. However, if those permanents enter the battlefield in the opposite order, your maximum hand size would be two."}], "securityStamp": "oval", "setCode": "SLD", "subtypes": [], "supertypes": [], "text": "You have no maximum hand size.\n{T}: Add {C}.", "type": "Land", "types": ["Land"], "uuid": "b8aa4163-1d3e-5e99-89c0-f9e5bf313937"}