{"artist": "Caio Monteiro", "availability": ["arena", "mtgo", "paper"], "boosterTypes": ["draft"], "borderColor": "black", "colorIdentity": ["U"], "colorIndicator": ["U"], "colors": ["U"], "convertedManaCost": 2.0, "edhrecRank": 17157, "faceConvertedManaCost": 0.0, "faceManaValue": 0.0, "faceName": "Cipherbound Spirit", "finishes": ["nonfoil", "foil"], "flavorText": "Rather than consort with demons, the Quietus Cult seeks wisdom from the dead.", "foreignData": [], "frameEffects": ["sunmoondfc"], "frameVersion": "2015", "hasFoil": true, "hasNonFoil": true, "identifiers": {"cardsphereId": "82062", "mcmId": "581909", "mcmMetaId": "346713", "mtgArenaId": "78870", "mtgjsonV4Id": "c69e7c5e-fe3f-5394-a983-62851e97cf6a", "mtgoId": "94472", "multiverseId": "540923", "scryfallId": "3c0fae23-1278-499f-9df7-4a29691726b1", "scryfallIllustrationId": "ac9f4af8-3a79-4588-823e-e56dc2c795fb", "scryfallOracleId": "6469c7fd-6c0f-4233-8c38-4742ddcf3c3f", "tcgplayerProductId": "253088"}, "keywords": ["Flying"], "language": "English", "layout": "transform", "legalities": {"alchemy": "Legal", "brawl": "Legal", "commander": "Legal", "duel": "Legal", "explorer": "Legal", "future": "Legal", "gladiator": "Legal", "historic": "Legal", "historicbrawl": "Legal", "legacy": "Legal", "modern": "Legal", "pioneer": "Legal", "standard": "Legal", "vintage": "Legal"}, "manaValue": 2.0, "name": "Soulcipher Board // Cipherbound Spirit", "number": "79", "originalText": "Flying\nCipherbound Spirit can block only creatures with flying.\n{3}{U}: Draw two cards, then discard a card.", "originalType": "Creature \u2014 Spirit", "otherFaceIds": ["885bcad2-125d-5733-9eec-0c09785a2a08"], "power": "3", "printings": ["DBL", "VOW"], "purchaseUrls": {"cardmarket": "https://mtgjson.com/links/01bc6670de0d1034", "tcgplayer": "https://mtgjson.com/links/e1a0c5c15707335e"}, "rarity": "uncommon", "rulings": [{"date": "2021-11-19", "text": "Soulcipher Board's last ability triggers when a creature card is put into a graveyard from anywhere. This is different than an ability that triggers when a creature dies. Notably, a noncreature card on the battlefield that becomes a creature and dies (such as an animated land) won't cause this ability to trigger. Similarly, a creature card on the battlefield that has been made a noncreature permanent (such as one enchanted with Minimus Containment) will cause this ability to trigger when that card is put into your graveyard."}, {"date": "2021-11-19", "text": "Token creatures dying never cause Soulcipher Board's last ability to trigger."}], "setCode": "VOW", "side": "b", "subtypes": ["Spirit"], "supertypes": [], "text": "Flying\nCipherbound Spirit can block only creatures with flying.\n{3}{U}: Draw two cards, then discard a card.", "toughness": "2", "type": "Creature \u2014 Spirit", "types": ["Creature"], "uuid": "5255c8f6-07bf-5be1-860c-7855402da55a"}