{"artist": "Li Tie", "availability": ["mtgo", "paper"], "boosterTypes": ["draft"], "borderColor": "black", "colorIdentity": ["B"], "colors": ["B"], "convertedManaCost": 4.0, "edhrecRank": 17922, "finishes": ["nonfoil", "foil"], "flavorText": "\"Crovax never passes up an opportunity to cause widespread misery.\"\n\u2014Belbe", "foreignData": [{"language": "German", "name": "Felsenburg-Disziplinierung", "text": "Jeder Spieler verliert 1 Lebenspunkt f\u00fcr jede Kreatur, die er kontrolliert.", "type": "Hexerei"}, {"language": "Spanish", "name": "Disciplina de la fortaleza"}, {"language": "French", "name": "Discipline de la forteresse"}, {"language": "Italian", "name": "Disciplina della Fortezza"}, {"language": "Japanese", "name": "\u8981\u585e\u306e\u898f\u5f8b"}, {"language": "Portuguese (Brazil)", "name": "Disciplina da Fortaleza"}], "frameVersion": "1997", "hasFoil": true, "hasNonFoil": true, "identifiers": {"cardKingdomFoilId": "39072", "cardKingdomId": "38072", "cardsphereId": "32964", "mcmId": "11796", "mcmMetaId": "5670", "mtgjsonV4Id": "b448fe5b-c5d5-5cda-849c-1370c4f0acea", "mtgoFoilId": "13786", "mtgoId": "13785", "multiverseId": "22374", "scryfallId": "46fa5472-5341-47cd-884e-fe2fcca12c0d", "scryfallIllustrationId": "6f8ab3c5-0eda-4f38-9931-4a2b6e8fe590", "scryfallOracleId": "90e46d04-9d53-4a24-aff0-f8c61e1db97d", "tcgplayerProductId": "7246"}, "language": "English", "layout": "normal", "legalities": {"commander": "Legal", "duel": "Legal", "legacy": "Legal", "modern": "Legal", "pauper": "Legal", "paupercommander": "Legal", "penny": "Legal", "premodern": "Legal", "vintage": "Legal"}, "manaCost": "{2}{B}{B}", "manaValue": 4.0, "name": "Stronghold Discipline", "number": "73", "originalText": "Each player loses 1 life for each creature he or she controls.", "originalType": "Sorcery", "printings": ["10E", "CNS", "NEM"], "purchaseUrls": {"cardKingdom": "https://mtgjson.com/links/1623d2af6adb71e4", "cardKingdomFoil": "https://mtgjson.com/links/9f24b622e2df1e22", "cardmarket": "https://mtgjson.com/links/42e0aefbe3d07ac6", "tcgplayer": "https://mtgjson.com/links/7822e0c2ac725c88"}, "rarity": "common", "rulings": [], "setCode": "NEM", "subtypes": [], "supertypes": [], "text": "Each player loses 1 life for each creature they control.", "type": "Sorcery", "types": ["Sorcery"], "uuid": "173587cb-0d00-561a-a4f2-f2df6605c550"}