{"artist": "Sandra Everingham", "availability": ["paper"], "boosterTypes": ["draft"], "borderColor": "black", "colorIdentity": [], "colors": [], "convertedManaCost": 3.0, "edhrecRank": 18211, "finishes": ["nonfoil"], "foreignData": [{"language": "Italian", "name": "Muro di Lance"}], "frameVersion": "1993", "hasFoil": false, "hasNonFoil": true, "identifiers": {"mcmId": "19410", "mcmMetaId": "6491", "mtgjsonV4Id": "be291a10-5d25-56ae-9ee7-65d7ef27d841", "scryfallId": "98d2a851-c48f-4012-a871-76d616404e34", "scryfallIllustrationId": "da8deec2-c60d-4ddb-ad4b-1bce0f900037", "scryfallOracleId": "ed836d84-ff1e-4af8-b4b8-314569b3faec", "tcgplayerProductId": "182437"}, "isReprint": true, "keywords": ["Defender", "First strike"], "language": "Italian", "layout": "normal", "legalities": {"commander": "Legal", "duel": "Legal", "legacy": "Legal", "modern": "Legal", "oldschool": "Legal", "pauper": "Legal", "paupercommander": "Legal", "penny": "Legal", "premodern": "Legal", "vintage": "Legal"}, "manaCost": "{3}", "manaValue": 3.0, "name": "Wall of Spears", "number": "148", "power": "2", "printings": ["4BB", "4ED", "5ED", "7ED", "8ED", "ATQ", "DPA", "PS11", "REN", "RIN"], "purchaseUrls": {"cardmarket": "https://mtgjson.com/links/c76d82e6c84f4aab", "tcgplayer": "https://mtgjson.com/links/66968ef879c40fa4"}, "rarity": "uncommon", "rulings": [], "setCode": "RIN", "subtypes": ["Wall"], "supertypes": [], "text": "Defender (This creature can't attack.)\nFirst strike", "toughness": "3", "type": "Artifact Creature \u2014 Wall", "types": ["Artifact", "Creature"], "uuid": "2fd968c2-53df-5d6b-b264-d982928371b6"}